entropymethod/__init__.py
entropymethod/core.py
entropymethod/model_selection.py
entropymethod/repeated.py
entropymethod/visual_test.py
entropymethod-0.3.12.dist-info/LICENSE
entropymethod-0.3.12.dist-info/METADATA
entropymethod-0.3.12.dist-info/WHEEL
entropymethod-0.3.12.dist-info/top_level.txt
entropymethod-0.3.12.dist-info/RECORD
