Metadata-Version: 2.1
Name: entropymethod
Version: 0.3.12
Summary: Estimate the number of clusters in your data set.
Home-page: https://github.com/mzelling/entropymethod
Author: Michael Zellinger
Author-email: mzellinger@ethz.ch
License: UNKNOWN
Project-URL: Bug Tracker, https://github.com/mzelling/entropymethod/issues
Platform: UNKNOWN
Classifier: Programming Language :: Python :: 3
Classifier: License :: OSI Approved :: MIT License
Classifier: Operating System :: OS Independent
Requires-Python: >=3.6
License-File: LICENSE
